amgd_optimizer/.DS_Store
amgd_optimizer/__init__.py
amgd_optimizer/.ipynb_checkpoints/__init__-checkpoint.py
amgd_optimizer/Example /__init__.py
amgd_optimizer/Example /basic_usage.py
amgd_optimizer/Example /.ipynb_checkpoints/basic_usage-checkpoint.py
amgd_optimizer/__pycache__/__init__.cpython-39.pyc
amgd_optimizer/core/__init__.py
amgd_optimizer/core/amgd_optimizer.py
amgd_optimizer/core/base.py
amgd_optimizer/core/.ipynb_checkpoints/__init__-checkpoint.py
amgd_optimizer/core/.ipynb_checkpoints/amgd_optimizer-checkpoint.py
amgd_optimizer/core/.ipynb_checkpoints/base-checkpoint.py
amgd_optimizer/regressors/__init__.py
amgd_optimizer/regressors/poisson_regression.py
amgd_optimizer/regressors/.ipynb_checkpoints/poisson_regression-checkpoint.py
amgd_optimizer/utils/__init__.py
amgd_optimizer/utils/metrics.py
amgd_optimizer/utils/validation.py
amgd_optimizer/utils/.ipynb_checkpoints/metrics-checkpoint.py
amgd_optimizer/utils/.ipynb_checkpoints/validation-checkpoint.py
amgd_optimizer-1.0.3.dist-info/METADATA
amgd_optimizer-1.0.3.dist-info/WHEEL
amgd_optimizer-1.0.3.dist-info/top_level.txt
amgd_optimizer-1.0.3.dist-info/RECORD
