Metadata-Version: 2.4
Name: amgd_optimizer
Version: 1.0.3
Summary: Adaptive Momentum Gradient Descent for Regularized Poisson Regression
Home-page: https://github.com/elbakari01/amgd_optimizer
Author: Ibrahim Bakari
Author-email: Ibrahim Bakari <2020913072@ogr.cu.edu.tr>
Maintainer: Ibrahim Bakari
Maintainer-email: Ibrahim Bakari <brhmbakari@gmail.com>
Project-URL: Homepage, https://github.com/elbakari01/amgd_optimizer
Project-URL: Documentation, https://amgd_optimizer.readthedocs.io/
Project-URL: Repository, https://github.com/elbakari01/amgd_optimizer.git
Project-URL: Bug Tracker, https://github.com/elbakari01/amgd_optimizer/issues
Project-URL: Changelog, https://github.com/elbakari01/amgd_optimizer/blob/main/CHANGELOG.md
Keywords: machine learning,optimization,poisson regression,regularization,sparse modeling,feature selection
Classifier: Development Status :: 3 - Alpha
Classifier: Intended Audience :: Science/Research
Classifier: Intended Audience :: Developers
Classifier: License :: OSI Approved :: MIT License
Classifier: Operating System :: OS Independent
Classifier: Programming Language :: Python :: 3
Classifier: Programming Language :: Python :: 3.8
Classifier: Programming Language :: Python :: 3.9
Classifier: Programming Language :: Python :: 3.10
Classifier: Programming Language :: Python :: 3.11
Classifier: Programming Language :: Python :: 3.12
Classifier: Topic :: Scientific/Engineering :: Artificial Intelligence
Classifier: Topic :: Scientific/Engineering :: Mathematics
Classifier: Topic :: Software Development :: Libraries :: Python Modules
Requires-Python: >=3.8
Requires-Dist: numpy>=1.19.0
Requires-Dist: scikit-learn>=1.0.0
Provides-Extra: dev
Requires-Dist: pytest>=6.0; extra == "dev"
Requires-Dist: pytest-cov>=2.0; extra == "dev"
Requires-Dist: black>=21.0; extra == "dev"
Requires-Dist: flake8>=3.8; extra == "dev"
Requires-Dist: mypy>=0.812; extra == "dev"
Requires-Dist: pre-commit>=2.15; extra == "dev"
Requires-Dist: isort>=5.0; extra == "dev"
Provides-Extra: docs
Requires-Dist: sphinx>=4.0; extra == "docs"
Requires-Dist: sphinx-rtd-theme>=1.0; extra == "docs"
Requires-Dist: sphinxcontrib-napoleon>=0.7; extra == "docs"
Requires-Dist: matplotlib>=3.3; extra == "docs"
Requires-Dist: myst-parser>=0.15; extra == "docs"
Provides-Extra: examples
Requires-Dist: jupyter>=1.0; extra == "examples"
Requires-Dist: seaborn>=0.11; extra == "examples"
Requires-Dist: pandas>=1.3; extra == "examples"
Requires-Dist: matplotlib>=3.3; extra == "examples"
Provides-Extra: all
Requires-Dist: pytest>=6.0; extra == "all"
Requires-Dist: pytest-cov>=2.0; extra == "all"
Requires-Dist: black>=21.0; extra == "all"
Requires-Dist: flake8>=3.8; extra == "all"
Requires-Dist: mypy>=0.812; extra == "all"
Requires-Dist: pre-commit>=2.15; extra == "all"
Requires-Dist: isort>=5.0; extra == "all"
Requires-Dist: sphinx>=4.0; extra == "all"
Requires-Dist: sphinx-rtd-theme>=1.0; extra == "all"
Requires-Dist: sphinxcontrib-napoleon>=0.7; extra == "all"
Requires-Dist: matplotlib>=3.3; extra == "all"
Requires-Dist: myst-parser>=0.15; extra == "all"
Requires-Dist: jupyter>=1.0; extra == "all"
Requires-Dist: seaborn>=0.11; extra == "all"
Requires-Dist: pandas>=1.3; extra == "all"
